spinque_query_api/__init__.py
spinque_query_api/api.py
spinque_query_api/authentication.py
spinque_query_api/exceptions.py
spinque_query_api/types.py
spinque_query_api/utils.py
spinque_query_api-0.0.4.dist-info/LICENSE
spinque_query_api-0.0.4.dist-info/METADATA
spinque_query_api-0.0.4.dist-info/WHEEL
spinque_query_api-0.0.4.dist-info/top_level.txt
spinque_query_api-0.0.4.dist-info/RECORD
