Metadata-Version: 2.1
Name: spinque-query-api
Version: 0.0.4
Summary: Library to use the Spinque Query API in your Python project.
Home-page: https://github.com/spinque/query-api-python/
Author: Spinque B.V.
Author-email: chris@spinque.com
License: MIT License
License-File: LICENSE
Requires-Dist: requests
